osslili/__init__.py
osslili/cli.py
osslili/core/__init__.py
osslili/core/generator.py
osslili/core/input_processor.py
osslili/core/models.py
osslili/data/__init__.py
osslili/data/exact_hashes.json
osslili/data/license_hashes.json
osslili/data/license_normalization.json
osslili/data/regex_patterns.json
osslili/data/spdx_licenses.json
osslili/data/spdx_licenses.py
osslili/detectors/__init__.py
osslili/detectors/license_detector.py
osslili/detectors/tlsh_detector.py
osslili/extractors/__init__.py
osslili/extractors/copyright_extractor.py
osslili/formatters/__init__.py
osslili/formatters/cyclonedx_formatter.py
osslili/formatters/evidence_formatter.py
osslili/formatters/kissbom_formatter.py
osslili/utils/__init__.py
osslili/utils/archive_extractor.py
osslili/utils/cache_manager.py
osslili/utils/config_loader.py
osslili/utils/file_scanner.py
osslili/utils/license_normalizer.py
osslili/utils/logging.py
osslili/utils/regex_matcher.py
osslili-1.6.3.dist-info/licenses/AUTHORS.md
osslili-1.6.3.dist-info/licenses/LICENSE
osslili-1.6.3.dist-info/METADATA
osslili-1.6.3.dist-info/WHEEL
osslili-1.6.3.dist-info/entry_points.txt
osslili-1.6.3.dist-info/top_level.txt
osslili-1.6.3.dist-info/RECORD
