Metadata-Version: 2.4
Name: osslili
Version: 1.6.3
Summary: Open Source License Identification Library
Author-email: "Oscar Valenzuela B." <oscar.valenzuela.b@gmail.com>
Maintainer-email: "Oscar Valenzuela B." <oscar.valenzuela.b@gmail.com>
License: Apache-2.0
Project-URL: Homepage, https://github.com/SemClone/osslili
Project-URL: Documentation, https://github.com/SemClone/osslili#readme
Project-URL: Repository, https://github.com/SemClone/osslili.git
Project-URL: Issues, https://github.com/SemClone/osslili/issues
Project-URL: Changelog, https://github.com/SemClone/osslili/blob/main/CHANGELOG.md
Keywords: license,attribution,legal,sbom,spdx,copyright,compliance,open-source,package-analysis
Classifier: Development Status :: 4 - Beta
Classifier: Intended Audience :: Developers
Classifier: Intended Audience :: Legal Industry
Classifier: Topic :: Software Development :: Libraries :: Python Modules
Classifier: Topic :: Software Development :: Documentation
Classifier: Topic :: System :: Software Distribution
Classifier: License :: OSI Approved :: Apache Software License
Classifier: Programming Language :: Python :: 3
Classifier: Programming Language :: Python :: 3.9
Classifier: Programming Language :: Python :: 3.10
Classifier: Programming Language :: Python :: 3.11
Classifier: Programming Language :: Python :: 3.12
Classifier: Operating System :: OS Independent
Requires-Python: >=3.9
License-File: LICENSE
License-File: AUTHORS.md
Requires-Dist: packageurl-python>=0.11.0
Requires-Dist: requests>=2.28.0
Requires-Dist: pyyaml>=6.0
Requires-Dist: click>=8.0.0
Requires-Dist: colorama>=0.4.0
Requires-Dist: fuzzywuzzy>=0.18.0
Provides-Extra: dev
Requires-Dist: pytest>=7.0.0; extra == "dev"
Requires-Dist: pytest-cov>=4.0.0; extra == "dev"
Requires-Dist: pytest-asyncio>=0.21.0; extra == "dev"
Requires-Dist: black>=23.0.0; extra == "dev"
Requires-Dist: flake8>=6.0.0; extra == "dev"
Requires-Dist: mypy>=1.0.0; extra == "dev"
Requires-Dist: isort>=5.12.0; extra == "dev"
Requires-Dist: pre-commit>=3.0.0; extra == "dev"
Provides-Extra: fast
Requires-Dist: python-Levenshtein>=0.20.0; extra == "fast"
Provides-Extra: tlsh
Requires-Dist: python-tlsh>=4.5.0; extra == "tlsh"
Provides-Extra: purl2src
Requires-Dist: purl2src>=0.1.0; extra == "purl2src"
Provides-Extra: cyclonedx
Requires-Dist: cyclonedx-python-lib>=4.0.0; extra == "cyclonedx"
Provides-Extra: ml
Requires-Dist: transformers>=4.30.0; extra == "ml"
Requires-Dist: torch>=2.0.0; extra == "ml"
Requires-Dist: scikit-learn>=1.3.0; extra == "ml"
Provides-Extra: all
Requires-Dist: osslili[cyclonedx,fast,purl2src,tlsh]; extra == "all"
Dynamic: license-file
